Mips 32 sim2/project_2.srcs/sources_1/new/processor.v
`timescale 1ns / 1ps
//////////////////////////////////////////////////////////////////////////////////
// Company: 
// Engineer: 
// 
// Create Date: 14.06.2025 14:30:52
// Design Name: 
// Module Name: processor
// Project Name: 
// Target Devices: 
// Tool Versions: 
// Description: 
// 
// Dependencies: 
// 
// Revision:
// Revision 0.01 - File Created
// Additional Comments:
// 
//////////////////////////////////////////////////////////////////////////////////


module pipe_MIPS32 (clk1, clk2); 
  input clk1, clk2;     
// Two-phase clock 
  reg [31:0] PC, IF_ID_IR, IF_ID_NPC; 
  reg [31:0] ID_EX_IR, ID_EX_NPC, ID_EX_A, ID_EX_B, ID_EX_Imm; 
  reg [2:0]  ID_EX_type, EX_MEM_type, MEM_WB_type; 
  reg [31:0] EX_MEM_IR, EX_MEM_ALUOut, EX_MEM_B; 
  reg        EX_MEM_cond; 
  reg [31:0] MEM_WB_IR, MEM_WB_ALUOut, MEM_WB_LMD; 
  reg [31:0] Reg [0:31];   
reg [31:0] Mem [0:1023];     

// Register bank (32 x 32) 
// 1024 x 32 memory 
parameter ADD=6'b000000, SUB=6'b000001, AND=6'b000010, OR=6'b000011,
          SLT=6'b000100, MUL=6'b000101, HLT=6'b111111, LW=6'b001000,
          SW=6'b001001, ADDI=6'b001010, SUBI=6'b001011,SLTI=6'b001100, 
          BNEQZ=6'b001101, BEQZ=6'b001110; 
parameter RR_ALU=3'b000, RM_ALU=3'b001, LOAD=3'b010, STORE=3'b011, 
            BRANCH=3'b100, HALT=3'b101; 
reg HALTED;    
       // Set after HLT instruction is completed (in WB stage) 
reg TAKEN_BRANCH;  
       // Required to disable instructions after branch 

always @(posedge clk1)        
// IF Stage 
    if (HALTED == 0) 
    begin 
      if (((EX_MEM_IR[31:26] == BEQZ) && (EX_MEM_cond == 1)) || 
          ((EX_MEM_IR[31:26] == BNEQZ) && (EX_MEM_cond == 0))) 
        begin 
          IF_ID_IR     <= #2 Mem[EX_MEM_ALUOut]; 
          TAKEN_BRANCH <= #2 1'b1; 
          IF_ID_NPC    <= #2 EX_MEM_ALUOut + 1; 
          PC           <= #2 EX_MEM_ALUOut + 1; 
        end 
      else 
       begin 
          IF_ID_IR     <=  #2 Mem[PC]; 
          IF_ID_NPC    <= #2 PC + 1; 
       end 
          PC           <= #2 PC + 1; 
    end 
always @(posedge clk2)        
// ID Stage 
    if (HALTED == 0) 
    begin 
      if (IF_ID_IR[25:21] == 5'b00000)  ID_EX_A <= 0; 
      else ID_EX_A     <=  #2 Reg[IF_ID_IR[25:21]];  // "rs" 
      
      if (IF_ID_IR[20:16] == 5'b00000)  ID_EX_B <= 0; 
      else ID_EX_B     <=  #2 Reg[IF_ID_IR[20:16]];  // "rt" 
      
      ID_EX_NPC   <=  #2 IF_ID_NPC; 
      ID_EX_IR    <=  #2 IF_ID_IR; 
      ID_EX_Imm   <=  #2 {{16{IF_ID_IR[15]}}, {IF_ID_IR[15:0]}};
      
      case (IF_ID_IR[31:26]) 
            ADD,SUB,AND,OR,SLT,MUL: ID_EX_type <= #2 RR_ALU; 
            ADDI,SUBI,SLTI:         ID_EX_type <= #2 RM_ALU; 
            LW:                     ID_EX_type <= #2 LOAD;                
            SW:                     ID_EX_type <= #2 STORE;              
            BNEQZ,BEQZ:             ID_EX_type <= #2 BRANCH;        
            HLT:                    ID_EX_type <= #2 HALT;      
           default:                 ID_EX_type <= #2 HALT;           
      endcase 
    end 

 always @(posedge clk1)        
// EX Stage 
    if (HALTED == 0) 
    begin 
      EX_MEM_type <= #2 ID_EX_type; 
      EX_MEM_IR   <= #2 ID_EX_IR; 
      TAKEN_BRANCH <= #2 0; 
      case (ID_EX_type) 
        RR_ALU:  begin 
                   case (ID_EX_IR[31:26])  // "opcode" 
                     ADD:  EX_MEM_ALUOut <= #2 ID_EX_A + ID_EX_B;    
                     SUB:  EX_MEM_ALUOut <= #2 ID_EX_A - ID_EX_B;    
                     AND:  EX_MEM_ALUOut <= #2 ID_EX_A & ID_EX_B;   
                     OR:   EX_MEM_ALUOut <= #2 ID_EX_A | ID_EX_B;    
                     SLT:  EX_MEM_ALUOut <= #2 ID_EX_A < ID_EX_B;   
                     MUL:  EX_MEM_ALUOut <= #2 ID_EX_A * ID_EX_B;    
                    default: EX_MEM_ALUOut <= #2 32'hxxxxxxxx; 
                   endcase 
                 end 
        RM_ALU:  begin 
                   case (ID_EX_IR[31:26])  // "opcode" 
                     ADDI:  EX_MEM_ALUOut <= #2 ID_EX_A + ID_EX_Imm;   
                     SUBI:  EX_MEM_ALUOut <= #2 ID_EX_A - ID_EX_Imm;    
                     SLTI:  EX_MEM_ALUOut <= #2 ID_EX_A < ID_EX_Imm;    
                    default: EX_MEM_ALUOut <= #2 32'hxxxxxxxx; 
                   endcase 
                 end 
        LOAD, STORE:  begin 
                    EX_MEM_ALUOut <= #2 ID_EX_A + ID_EX_Imm; 
                    EX_MEM_B      <= #2 ID_EX_B; 
                    end  
        BRANCH:  begin 
                    EX_MEM_ALUOut <= #2 ID_EX_NPC + ID_EX_Imm; 
                    EX_MEM_cond   <= #2 (ID_EX_A == 0); 
                 end 
      endcase 
    end
  always @(posedge clk2)        // MEM Stage 
    if (HALTED == 0) 
    begin 
      MEM_WB_type <= EX_MEM_type; 
      MEM_WB_IR   <= #2 EX_MEM_IR; 
      case (EX_MEM_type) 
        RR_ALU, RM_ALU: MEM_WB_ALUOut <= #2 EX_MEM_ALUOut; 
        LOAD:           MEM_WB_LMD <= #2 Mem[EX_MEM_ALUOut];   
        STORE:          if (TAKEN_BRANCH == 0)  // Disable write  
                            Mem[EX_MEM_ALUOut] <= #2 EX_MEM_B;
      endcase 
    end 
 always @(posedge clk1)        
    begin 
        if (TAKEN_BRANCH == 0)   
            case (MEM_WB_type) 
                RR_ALU:   Reg[MEM_WB_IR[15:11]] <= #2 MEM_WB_ALUOut; // "rd" 
                RM_ALU:   Reg[MEM_WB_IR[20:16]] <= #2 MEM_WB_ALUOut; // "rt"
                LOAD:     Reg[MEM_WB_IR[20:16]] <= #2 MEM_WB_LMD; // "rt" 
                HALT:     HALTED <= #2 1'b1; 
            endcase 
    end 
endmodule       
            
 

                     


 
                                                  //

Mips 32 sim2/project_2.srcs/sources_1/new/Mips_tb2.v
`timescale 1ns / 1ps
//////////////////////////////////////////////////////////////////////////////////
// Company: 
// Engineer: 
// 
// Create Date: 14.06.2025 16:26:08
// Design Name: 
// Module Name: Mips_tb2
// Project Name: 
// Target Devices: 
// Tool Versions: 
// Description: 
// 
// Dependencies: 
// 
// Revision:
// Revision 0.01 - File Created
// Additional Comments:
// 
//////////////////////////////////////////////////////////////////////////////////

module test_mips32; 
  reg clk1, clk2; 
  integer k; 
  pipe_MIPS32 mips (clk1, clk2); 
     
  initial 
    begin 
      clk1 = 0; clk2 = 0; 
      repeat (50)                       // Generating two-phase clock 
        begin 
          #5 clk1 = 1;  #5 clk1 = 0; 
          #5 clk2 = 1;  #5 clk2 = 0; 
        end 
    end 
  initial 
    begin 
      for (k=0; k<31; k=k+1) 
        mips.Reg[k] = k; 
	
      mips.Mem[0] = 32'h28010078;  // ADDI  R1,R0,120 
      mips.Mem[1] = 32'h0c631800;  // OR    R3,R3,R3 -- dummy instr. 
      mips.Mem[2] = 32'h20220000;  // LW    R2,0(R1) 
      mips.Mem[3] = 32'h0c631800;  // OR    R3,R3,R3 -- dummy instr. 
      mips.Mem[4] = 32'h2842002d;  // ADDI  R2,R2,45 
      mips.Mem[5] = 32'h0c631800;  // OR    R3,R3,R3 -- dummy instr. 
      mips.Mem[6] = 32'h24220001;  // SW    R2,1(R1) 
      mips.Mem[7] = 32'hfc000000;  // HLT 
      mips.Mem[120] = 85; 
   
      mips.PC = 0; 
      mips.HALTED = 0; 
      mips.TAKEN_BRANCH = 0; 
      #500  $display ("Mem[120]: %4d \nMem[121]: %4d", 
      mips.Mem[120], mips.Mem[121]); 
    end 
  initial 
    begin 
      $dumpfile ("mips.vcd"); 
      $dumpvars (0, test_mips32); 
      #600 $finish; 
    end 
endmodule

Mips 32 sim2/project_2.sim/sim_1/behav/xsim/mips.vcd
$date
   Sat Jun 14 17:15:40 2025
$end

$version
  2024.2.0
  $dumpfile ("mips.vcd") 
$end

$timescale
  1ps
$end

$scope module test_mips32 $end
$var reg 1 ! clk1 $end
$var reg 1 " clk2 $end
$var integer 32 # k [31:0] $end
$scope module mips $end
$var wire 1 $ clk1 $end
$var wire 1 % clk2 $end
$var reg 32 & PC [31:0] $end
$var reg 32 ' IF_ID_IR [31:0] $end
$var reg 32 ( IF_ID_NPC [31:0] $end
$var reg 32 ) ID_EX_IR [31:0] $end
$var reg 32 * ID_EX_NPC [31:0] $end
$var reg 32 + ID_EX_A [31:0] $end
$var reg 32 , ID_EX_B [31:0] $end
$var reg 32 - ID_EX_Imm [31:0] $end
$var reg 3 . ID_EX_type [2:0] $end
$var reg 3 / EX_MEM_type [2:0] $end
$var reg 3 0 MEM_WB_type [2:0] $end
$var reg 32 1 EX_MEM_IR [31:0] $end
$var reg 32 2 EX_MEM_ALUOut [31:0] $end
$var reg 32 3 EX_MEM_B [31:0] $end
$var reg 1 4 EX_MEM_cond $end
$var reg 32 5 MEM_WB_IR [31:0] $end
$var reg 32 6 MEM_WB_ALUOut [31:0] $end
$var reg 32 7 MEM_WB_LMD [31:0] $end
$var reg 1 8 HALTED $end
$var reg 1 9 TAKEN_BRANCH $end
$upscope $end
$upscope $end
$enddefinitions $end

#0
$dumpvars
0!
0"
b11111 #
0$
0%
b0 &
bx '
bx (
bx )
bx *
bx +
bx ,
bx -
bx .
bx /
bx 0
bx 1
bx 2
bx 3
x4
bx 5
bx 6
bx 7
08
09
$end

#5000
1!
1$

#7000
b1 &
b101000000000010000000001111000 '
b1 (

#10000
0!
0$

#15000
1"
1%
b0 +

#17000
b101000000000010000000001111000 )
b1 *
b1 ,
b1111000 -
b1 .

#20000
0"
0%

#25000
1!
1$

#27000
b10 &
b1100011000110001100000000000 '
b10 (
b1 /
b101000000000010000000001111000 1
b1111000 2

#30000
0!
0$

#35000
1"
1%
b1 0

#37000
b1100011000110001100000000000 )
b10 *
b11 +
b11 ,
b1100000000000 -
b0 .
b101000000000010000000001111000 5
b1111000 6

#40000
0"
0%

#45000
1!
1$

#47000
b11 &
b100000001000100000000000000000 '
b11 (
b0 /
b1100011000110001100000000000 1
b11 2

#50000
0!
0$

#55000
1"
1%
b0 0

#57000
b100000001000100000000000000000 )
b11 *
b1111000 +
b10 ,
b0 -
b10 .
b1100011000110001100000000000 5
b11 6

#60000
0"
0%

#65000
1!
1$

#67000
b100 &
b1100011000110001100000000000 '
b100 (
b10 /
b100000001000100000000000000000 1
b1111000 2
b10 3

#70000
0!
0$

#75000
1"
1%
b10 0

#77000
b1100011000110001100000000000 )
b100 *
b11 +
b11 ,
b1100000000000 -
b0 .
b100000001000100000000000000000 5
b1010101 7

#80000
0"
0%

#85000
1!
1$

#87000
b101 &
b101000010000100000000000101101 '
b101 (
b0 /
b1100011000110001100000000000 1
b11 2

#90000
0!
0$

#95000
1"
1%
b0 0

#97000
b101000010000100000000000101101 )
b101 *
b1010101 +
b1010101 ,
b101101 -
b1 .
b1100011000110001100000000000 5

#100000
0"
0%

#105000
1!
1$

#107000
b110 &
b1100011000110001100000000000 '
b110 (
b1 /
b101000010000100000000000101101 1
b10000010 2

#110000
0!
0$

#115000
1"
1%
b1 0

#117000
b1100011000110001100000000000 )
b110 *
b11 +
b11 ,
b1100000000000 -
b0 .
b101000010000100000000000101101 5
b10000010 6

#120000
0"
0%

#125000
1!
1$

#127000
b111 &
b100100001000100000000000000001 '
b111 (
b0 /
b1100011000110001100000000000 1
b11 2

#130000
0!
0$

#135000
1"
1%
b0 0

#137000
b100100001000100000000000000001 )
b111 *
b1111000 +
b10000010 ,
b1 -
b11 .
b1100011000110001100000000000 5
b11 6

#140000
0"
0%

#145000
1!
1$

#147000
b1000 &
b11111100000000000000000000000000 '
b1000 (
b11 /
b100100001000100000000000000001 1
b1111001 2
b10000010 3

#150000
0!
0$

#155000
1"
1%
b0 +
b0 ,
b11 0

#157000
b11111100000000000000000000000000 )
b1000 *
b0 -
b101 .
b100100001000100000000000000001 5

#160000
0"
0%

#165000
1!
1$

#167000
b1001 &
bx '
b1001 (
b101 /
b11111100000000000000000000000000 1

#170000
0!
0$

#175000
1"
1%
b101 0

#177000
bx )
b1001 *
bx +
bx ,
bx -
b11111100000000000000000000000000 5

#180000
0"
0%

#185000
1!
1$

#187000
b1010 &
b1010 (
bx 1
18

